[
    {
        "id": 2,
        "nombre": "Chilemorrones",
        "jugadores": [
            {
                "id_jugador": 28,
                "es_lider": true
            },
            {
                "id_jugador": 29,
                "es_lider": false
            }
        ]
    },
    {
        "id": 4,
        "nombre": "TEAM 2",
        "jugadores": [
            {
                "id_jugador": 30,
                "es_lider": true
            },
            {
                "id_jugador": 31,
                "es_lider": false
            }
        ]
    },
    {
        "id": 5,
        "nombre": "TEAM 1",
        "jugadores": [
            {
                "id_jugador": 32,
                "es_lider": true
            },
            {
                "id_jugador": 33,
                "es_lider": false
            }
        ]
    },
    {
        "id": 6,
        "nombre": "Equipo Bala",
        "jugadores": [
            {
                "id_jugador": 26,
                "es_lider": false
            },
            {
                "id_jugador": 27,
                "es_lider": true
            }
        ]
    },
    {
        "id": 7,
        "nombre": "BUG",
        "jugadores": [
            {
                "id_jugador": 32,
                "es_lider": true
            },
            {
                "id_jugador": 33,
                "es_lider": false
            },
            {
                "id_jugador": 26,
                "es_lider": false
            },
            {
                "id_jugador": 27,
                "es_lider": false
            },
            {
                "id_jugador": 28,
                "es_lider": false
            },
            {
                "id_jugador": 29,
                "es_lider": false
            },
            {
                "id_jugador": 30,
                "es_lider": false
            },
            {
                "id_jugador": 31,
                "es_lider": false
            }
        ]
    }
]